{
  "lastUpdated": "2026-03-09 02:49:13",
  "totalCount": 31,
  "sources": {
    "Eeo": 1,
    "News_Baidu": 10,
    "Imobile": 1,
    "Chinanews": 1,
    "News_Seehua": 1,
    "Times of India": 1,
    "PerthNow": 1,
    "The Star": 1,
    "Benzinga": 3,
    "The Guardian": 1,
    "CNBC": 2,
    "The Manila Times": 1,
    "Markets Insider": 1,
    "Interesting Engineering": 1,
    "Investor's Business Daily": 1,
    "NextBigFuture.com": 1,
    "MarketScreener": 1,
    "Business Today": 1,
    "Barchart": 1
  },
  "news": [
    {
      "id": "http://www.eeo.com.cn/2026/0308/807307.shtml",
      "title": "莲花CEO冯擎峰:已暂缓出口中东,但加拿大市场将弥补部分损失",
      "summary": "冯擎峰认为,工业领域的企业并不是只有销量规模特别大,才能生存得好。莲花的目标是,在规模还不大时就能实现盈利。...",
      "source": "Eeo",
      "date": "2026-03-08",
      "url": "http://www.eeo.com.cn/2026/0308/807307.shtml"
    },
    {
      "id": "http://baijiahao.baidu.com/s?id=1859058419595233359",
      "title": "两会经济策|自动驾驶,安全与责任边界在哪?",
      "summary": "工业和信息化部部长李乐成3月5日在十四届全国人大四次会议首场“部长通道”上,点名“新能源汽车”“自动驾驶汽车”。他提到,2026年工信部将大力推动人工智能(AI)和制造业双向奔赴,全力推进新一代人工智...",
      "source": "News_Baidu",
      "date": "2026-03-08",
      "url": "http://baijiahao.baidu.com/s?id=1859058419595233359"
    },
    {
      "id": "http://baijiahao.baidu.com/s?id=1859087934893950048",
      "title": "上海的女警这么过“三八”国际妇女节",
      "summary": "近日,2025年度“全国巾帼文明岗”名单公布,上海市公安局松江分局交通管理支队女子岗组获得这一荣誉。这支队伍也是全市一万余名女民警、女辅警的一个缩影。3月8日妇女节,许多女警仍坚守在岗,在交通疏导、反诈劝阻、社区服务等日...",
      "source": "News_Baidu",
      "date": "2026-03-08",
      "url": "http://baijiahao.baidu.com/s?id=1859087934893950048"
    },
    {
      "id": "http://baijiahao.baidu.com/s?id=1859094660106615586",
      "title": "别只羡慕上海的1元公交!票价1元、手机预约、动态接..",
      "summary": "“太超前了!”3月5日,有网友在社交媒体上分享,上海陆家嘴可以打网约公交车了,票价仅需1元。据了解,这种网约公交车系统能在后台自动生成最优导航线路,实时推送至驾驶室终端,司机根据系统生成路线行驶,安全...",
      "source": "News_Baidu",
      "date": "2026-03-08",
      "url": "http://baijiahao.baidu.com/s?id=1859094660106615586"
    },
    {
      "id": "http://baijiahao.baidu.com/s?id=1859092203925876180",
      "title": "巾帼不让须眉 撑起平安建设“半边天”",
      "summary": "2025年度“全国巾帼文明岗”名单近日正式揭晓,上海市公安局松江公安分局交通管理支队女子岗组光荣上榜。这份荣誉是她们以柔肩护通途的最好见证,也映照出全市公安女警最美的巾帼风采。在上海,一万余女民警、女...",
      "source": "News_Baidu",
      "date": "2026-03-08",
      "url": "http://baijiahao.baidu.com/s?id=1859092203925876180"
    },
    {
      "id": "http://news.imobile.com.cn/articles/2026/0308/233696.shtml",
      "title": "5分钟充好,9分钟充饱,比亚迪闪充补上新能源转型最后一块拼图",
      "summary": "“没有人比我们比亚迪更懂电池。” 在3月5日的比亚迪“闪充中国 改变世界”发布会上,比亚迪集团董事长兼总裁王传福发布了比亚迪迪二代刀片电池及闪充技术,并宣布了一个极具颠覆性的充电速度: 5分钟从10%充到70%; 9分钟从10%充到97%; 零下30度,充电时间也只增加3分钟。 比亚迪将其概括为——5分钟充好,9分钟充饱,零下30度只多3分钟。 这意味着新能源汽车的充电速度记录再一次被比亚迪刷新,...",
      "source": "Imobile",
      "date": "2026-03-08",
      "url": "http://news.imobile.com.cn/articles/2026/0308/233696.shtml"
    },
    {
      "id": "http://baijiahao.baidu.com/s?id=1859087646754118359",
      "title": "智话巾帼绽芳华 暖“新”关爱显真情——昆明市妇联举..",
      "summary": "昆明信息港讯记者李红鸾春潮涌动暖人心,巾帼奋进绽芳华。3月6日下午,在第116个“三八”国际劳动妇女节即将到来之际,昆明市妇联在玺尊龙酒店举办2026年“智话巾帼绽芳华”暖“新”慰问活动,向奋战在全市...",
      "source": "News_Baidu",
      "date": "2026-03-08",
      "url": "http://baijiahao.baidu.com/s?id=1859087646754118359"
    },
    {
      "id": "https://www.chinanews.com.cn/sh/2026/03-08/10583512.shtml",
      "title": "铁路女警“三重奏”:按停危险、撬开人心、守住闸口",
      "summary": "中新网昆明3月8日电 题:铁路女警“三重奏”:按停危险、撬开人心、守住闸口...",
      "source": "Chinanews",
      "date": "2026-03-08",
      "url": "https://www.chinanews.com.cn/sh/2026/03-08/10583512.shtml"
    },
    {
      "id": "http://baijiahao.baidu.com/s?id=1859082735042730920",
      "title": "神州租车:女性租车用户稳步增长 自驾里程突破5亿公..",
      "summary": "神州租车:女性租车用户稳步增长自驾里程突破5亿公里 随着女性出行自主意识不断提升,租车自驾正成为越来越多女性用户探索城市与远方的重要方式。在“三八”国际妇女节来临之际,神州租车发布《当代女性租车...",
      "source": "News_Baidu",
      "date": "2026-03-08",
      "url": "http://baijiahao.baidu.com/s?id=1859082735042730920"
    },
    {
      "id": "http://baijiahao.baidu.com/s?id=1859079054844145906",
      "title": "这个全国三八红旗集体 平均年龄不到26岁",
      "summary": "通讯员王天悦中青报·中青网记者樊江涛自2022年9月河北省石家庄市公安局巡警特警支队女子勤务大队组建以来,这群平均年龄不到26岁的姑娘们用忠诚与坚韧勾勒出警营“她力量”的动人轮廓,以“为人民服务”的使...",
      "source": "News_Baidu",
      "date": "2026-03-08",
      "url": "http://baijiahao.baidu.com/s?id=1859079054844145906"
    },
    {
      "id": "http://baijiahao.baidu.com/s?id=1859078711228991773",
      "title": "渝地芳华 她力绽放|从空乘到机长 杜倩:以温柔力量..",
      "summary": "央广网重庆3月8日消息(记者王海)春风送暖,芳华绽放。在三八妇女节到来之际,让我们聆听重庆航空首位女飞行员杜倩的成长故事。她跨越职业赛道、逐梦蓝天,用...",
      "source": "News_Baidu",
      "date": "2026-03-08",
      "url": "http://baijiahao.baidu.com/s?id=1859078711228991773"
    },
    {
      "id": "https://news.seehua.com/post/1450625",
      "title": "美里交警取缔街头飙车 开出40张罚单扣10辆摩托",
      "summary": "(美里8日讯)美里警区交通调查与执法组展开“街头流氓行动”(Op Samseng Jalanan),共开出40 [...]...",
      "source": "News_Seehua",
      "date": "2026-03-08",
      "url": "https://news.seehua.com/post/1450625"
    },
    {
      "id": "http://baijiahao.baidu.com/s?id=1859071567926882439",
      "title": "从“点云”到“图像”,华为乾崑发布896线激光雷达",
      "summary": "896线激光雷达“一体双焦”的设计,既保留了视野广度,又兼顾了远距离的细节捕捉。华为乾崑供图中国青年报客户端讯(中青报·中青网记者张真齐)近日,华为乾崑正式推出新一代双光路图像级激光雷达,以896线的...",
      "source": "News_Baidu",
      "date": "2026-03-08",
      "url": "http://baijiahao.baidu.com/s?id=1859071567926882439"
    },
    {
      "id": "http://baijiahao.baidu.com/s?id=1859055747092577736",
      "title": "正是山花烂漫时,她在丛中笑",
      "summary": "春风回暖,万物生长的季节,第116个“三八”国际妇女节与贵州赏花季的芬芳如期相遇。放眼黔贵大地,毕节百里杜鹃已绘出“地球彩带”,贵阳贵安的樱花绽放粉色云霞,黔东南丹寨龙泉山架起赤色“天梯”,黔西南万峰...",
      "source": "News_Baidu",
      "date": "2026-03-08",
      "url": "http://baijiahao.baidu.com/s?id=1859055747092577736"
    },
    {
      "id": "https://timesofindia.indiatimes.com/auto/cars/us-to-host-self-driving-safety-forum-with-waymo-zoox-and-aurora-ceos/articleshow/129260588.cms",
      "title": "driving safety forum with Waymo, Zoox and Aurora CEOs",
      "summary": "Cars News: The National Highway Traffic Safety Administration (NHTSA) will host a national autonomous vehicle safety forum on Tuesday, bringing together leaders ....",
      "source": "Times of India",
      "date": "2026-03-08",
      "url": "https://timesofindia.indiatimes.com/auto/cars/us-to-host-self-driving-safety-forum-with-waymo-zoox-and-aurora-ceos/articleshow/129260588.cms"
    },
    {
      "id": "https://www.perthnow.com.au/news/transport/driving-change-inside-the-autonomous-car-revolution-c-21862252",
      "title": "Driving change: inside the autonomous car revolution",
      "summary": "More self-driving cars will navigate streets around the world this year but some are yet to be convinced the technology is roadworthy....",
      "source": "PerthNow",
      "date": "2026-03-06",
      "url": "https://www.perthnow.com.au/news/transport/driving-change-inside-the-autonomous-car-revolution-c-21862252"
    },
    {
      "id": "https://www.thestar.com.my/tech/tech-news/2026/03/06/us-agency-to-hold-self-driving-safety-forum-with-ceos-of-waymo-zoox-aurora",
      "title": "US agency to hold self-driving safety forum with CEOs of Waymo, Zoox, Aurora",
      "summary": "WASHINGTON, March ⁠6 (Reuters) - The National Highway ⁠Traffic Safety Administration will ‌hold a national autonomous vehicle safety forum that will include the ​CEOs of self-driving ⁠companies Waymo,...",
      "source": "The Star",
      "date": "2026-03-06",
      "url": "https://www.thestar.com.my/tech/tech-news/2026/03/06/us-agency-to-hold-self-driving-safety-forum-with-ceos-of-waymo-zoox-aurora"
    },
    {
      "id": "https://www.benzinga.com/markets/tech/26/03/51063089/plusai-shatters-ai-speed-records-with-superdrive-6-0-targets-full-driverless-launch-in-2026",
      "title": "PlusAI Shatters AI Speed Records With SuperDrive 6.0, Targets Full Driverless Launch In 2026",
      "summary": "PlusAI just unveiled SuperDrive 6.0, a breakthrough in autonomous trucking that trains AI 10X faster. Discover how their new night-driving tech and 7 million miles of data are paving the way for a 202...",
      "source": "Benzinga",
      "date": "2026-03-05",
      "url": "https://www.benzinga.com/markets/tech/26/03/51063089/plusai-shatters-ai-speed-records-with-superdrive-6-0-targets-full-driverless-launch-in-2026"
    },
    {
      "id": "https://www.theguardian.com/technology/2026/mar/04/nvidia-uk-wealth-fund-invest-british-autonomous-driving-startup-oxa",
      "title": "Nvidia and UK Wealth Fund to invest in British autonomous driving startup Oxa",
      "summary": "Oxford-based firm has raised $103m for commercial development of software for self-driving industrial vehicles...",
      "source": "The Guardian",
      "date": "2026-03-04",
      "url": "https://www.theguardian.com/technology/2026/mar/04/nvidia-uk-wealth-fund-invest-british-autonomous-driving-startup-oxa"
    },
    {
      "id": "https://www.cnbc.com/2026/03/04/bank-of-america-upgrades-tesla-calls-it-the-clear-leader-in-autonomous-driving.html",
      "title": "Bank of America upgrades Tesla, calls it the clear leader in autonomous driving",
      "summary": "Tesla's advances in autonomous driving and robotaxi services could drive its next phase of growth, Bank of America said....",
      "source": "CNBC",
      "date": "2026-03-04",
      "url": "https://www.cnbc.com/2026/03/04/bank-of-america-upgrades-tesla-calls-it-the-clear-leader-in-autonomous-driving.html"
    },
    {
      "id": "https://www.manilatimes.net/2026/03/04/tmt-newswire/globenewswire/weride-to-report-fourth-quarter-and-full-year-2025-financial-results-on-monday-march-23-2026/2292997",
      "title": "WeRide to Report Fourth Quarter and Full Year 2025 Financial Results on Monday, March 23, 2026",
      "summary": "NEW YORK, March 04, 2026 (GLOBE NEWSWIRE) -- WeRide Inc. ('WeRide” or the 'Company”) (Nasdaq: WRD), a global leader in autonomous driving technology, today announced that it will release its unaudited...",
      "source": "The Manila Times",
      "date": "2026-03-04",
      "url": "https://www.manilatimes.net/2026/03/04/tmt-newswire/globenewswire/weride-to-report-fourth-quarter-and-full-year-2025-financial-results-on-monday-march-23-2026/2292997"
    },
    {
      "id": "https://markets.businessinsider.com/news/stocks/tesla-model-y-completes-huge-fsd-run-without-intervention-tesla-stock-nasdaq-tsla-surges-1035897933",
      "title": "Tesla Model Y Completes Huge FSD Run Without Intervention, Tesla Stock (NASDAQ:TSLA) Surges",
      "summary": "Finally, a day in which the news about a company matches what happens in its stock price. Those who were concerned about just how well electric ......",
      "source": "Markets Insider",
      "date": "2026-03-04",
      "url": "https://markets.businessinsider.com/news/stocks/tesla-model-y-completes-huge-fsd-run-without-intervention-tesla-stock-nasdaq-tsla-surges-1035897933"
    },
    {
      "id": "https://interestingengineering.com/transportation/tesla-full-self-driving-reaches-8-billion-milestone",
      "title": "Tesla’s Full Self Driving clocks over 8 billion miles cumulatively",
      "summary": "Tesla's Full Self-Driving (FSD) fleet has cumulatively clocked over 8 billion miles which will be used as training data for its advanced driver assistance system (ADAS)....",
      "source": "Interesting Engineering",
      "date": "2026-03-02",
      "url": "https://interestingengineering.com/transportation/tesla-full-self-driving-reaches-8-billion-milestone"
    },
    {
      "id": "https://www.investors.com/news/tesla-cybercab-coming-to-europe/",
      "title": "Musk Says Tesla FSD, Cybercab, Optimus Coming To Europe",
      "summary": "Tesla's FSD platform could approved as soon as next month in Holland. Elon Musk said Optimus and Cybercab to be built at German factory....",
      "source": "Investor's Business Daily",
      "date": "2026-02-27",
      "url": "https://www.investors.com/news/tesla-cybercab-coming-to-europe/"
    },
    {
      "id": "https://www.nextbigfuture.com/2026/02/elon-interviewed-at-gigaberlin-with-news-on-fsd-march-20-netherlands-cybercab-optimus.html",
      "title": "Elon Interviewed At GigaBerlin- With News on FSD March 20 Netherlands, Cybercab, Optimus",
      "summary": "Elon drops the big things on FSD, cybercab and optimus, battery and cybercab factory in Europe. If authorities cooperate, Tesla would make Gigaberlin the...",
      "source": "NextBigFuture.com",
      "date": "2026-02-27",
      "url": "https://www.nextbigfuture.com/2026/02/elon-interviewed-at-gigaberlin-with-news-on-fsd-march-20-netherlands-cybercab-optimus.html"
    },
    {
      "id": "https://www.benzinga.com/markets/tech/26/02/50859270/ross-gerber-warns-teslas-mad-max-fsd-mode-is-basically-unsafe-following-240-million-autopilot-liability-verdict",
      "title": "Ross Gerber Warns Tesla's 'Mad Max' FSD Mode Is 'Basically Unsafe' Following $240 Million Autopilot Liability Verdict",
      "summary": "Ross Gerber, co-founder of investment firm Gerber Kawasaki, issued a stern warning on Wednesday regarding the safety of Tesla Inc.'s (TSLA) autonomous driving software....",
      "source": "Benzinga",
      "date": "2026-02-25",
      "url": "https://www.benzinga.com/markets/tech/26/02/50859270/ross-gerber-warns-teslas-mad-max-fsd-mode-is-basically-unsafe-following-240-million-autopilot-liability-verdict"
    },
    {
      "id": "https://www.marketscreener.com/news/tesla-reportedly-sues-california-dmv-to-reverse-fsd-advertising-related-ruling-ce7e5cdad980f72c",
      "title": "Tesla Reportedly Sues California DMV to Reverse FSD Advertising-Related Ruling",
      "summary": "Tesla has filed a lawsuit against California's Department of Motor Vehicles in a bid to reverse a ruling that found the electric vehicle maker breached the law by falsely promoting its cars'......",
      "source": "MarketScreener",
      "date": "2026-02-24",
      "url": "https://www.marketscreener.com/news/tesla-reportedly-sues-california-dmv-to-reverse-fsd-advertising-related-ruling-ce7e5cdad980f72c"
    },
    {
      "id": "https://www.benzinga.com/markets/tech/26/02/50804700/elon-musks-tesla-sues-california-dmv-following-false-advertising-row-around-fsd-autopilot",
      "title": "Elon Musk's Tesla Sues California DMV Following False Advertising Row Around FSD, Autopilot",
      "summary": "Tesla sues California DMV over false advertiser label for Autopilot, alleges DMV did not prove claims about confusion among consumers....",
      "source": "Benzinga",
      "date": "2026-02-24",
      "url": "https://www.benzinga.com/markets/tech/26/02/50804700/elon-musks-tesla-sues-california-dmv-following-false-advertising-row-around-fsd-autopilot"
    },
    {
      "id": "https://www.cnbc.com/2026/02/23/tesla-sues-california-dmv-to-reverse-false-advertising-ruling-on-fsd.html",
      "title": "Tesla sues California DMV to reverse false advertising ruling on FSD",
      "summary": "California's DMV previously ruled that Tesla falsely promoted its cars' self-driving capabilities....",
      "source": "CNBC",
      "date": "2026-02-23",
      "url": "https://www.cnbc.com/2026/02/23/tesla-sues-california-dmv-to-reverse-false-advertising-ruling-on-fsd.html"
    },
    {
      "id": "https://www.businesstoday.in/technology/news/story/tesla-begins-hiring-ai-hardware-engineers-in-bengaluru-signals-deeper-tech-expansion-in-india-517391-2026-02-21",
      "title": "Tesla begins hiring AI hardware engineers in Bengaluru, signals deeper tech expansion in India",
      "summary": "According to the job description, the role sits within the AI & Robotics division under Engineering and R&D and will contribute to building hardware that powers Tesla’s neural-network-driven technolog...",
      "source": "Business Today",
      "date": "2026-02-21",
      "url": "https://www.businesstoday.in/technology/news/story/tesla-begins-hiring-ai-hardware-engineers-in-bengaluru-signals-deeper-tech-expansion-in-india-517391-2026-02-21"
    }
  ]
}